pardon/__init__.py
pardon/audits.py
pardon/config.py
pardon/formats.py
pardon/make_rules.py
pardon/pardon.py
pardon/pardon_api.py
pardon/pardon_encode.py
pardon/pardon_models.py
pardon/pardon_options.py
pardon/pardon_predict.py
pardon/pardon_target.py
pardon/pardon_transforms.py
pardon/pickles.py
pardon/statics.py
pardon/utility.py
pardon/visuals.py
pardon/app_build/__init__.py
pardon/app_build/app.py
pardon/app_build/poc_app.py
pardon/app_build/statics.py
pardon-2.0.5.dist-info/LICENSE
pardon-2.0.5.dist-info/METADATA
pardon-2.0.5.dist-info/WHEEL
pardon-2.0.5.dist-info/top_level.txt
pardon-2.0.5.dist-info/RECORD
