Metadata-Version: 2.1
Name: pardon
Version: 2.0.5
Summary: The Data Transformation and Machine Learning Accelerator
Requires-Python: >=3.8.1, <3.11
License-File: LICENSE
Requires-Dist: category-encoders (==2.3.0)
Requires-Dist: click (==7.1.2)
Requires-Dist: cloudpickle (==2.0.0)
Requires-Dist: colorama (==0.4.4)
Requires-Dist: cycler (==0.11.0)
Requires-Dist: dill (==0.3.4)
Requires-Dist: Flask (==1.1.4)
Requires-Dist: fonttools (==4.33.3)
Requires-Dist: imbalanced-learn (==0.9.0)
Requires-Dist: imblearn (==0.0)
Requires-Dist: itsdangerous (==1.1.0)
Requires-Dist: Jinja2 (==2.11.3)
Requires-Dist: joblib (==1.1.0)
Requires-Dist: kiwisolver (==1.4.2)
Requires-Dist: llvmlite (==0.39.1)
Requires-Dist: MarkupSafe (==2.0.1)
Requires-Dist: matplotlib (==3.5.1)
Requires-Dist: neattext (==0.1.3)
Requires-Dist: nltk (==3.7)
Requires-Dist: numba (==0.56.4)
Requires-Dist: numpy (==1.23.4)
Requires-Dist: openpyxl (==3.0.10)
Requires-Dist: packaging (==21.3)
Requires-Dist: pandas (==1.4.3)
Requires-Dist: patsy (==0.5.2)
Requires-Dist: Pillow (==9.1.0)
Requires-Dist: plotly (==5.6.0)
Requires-Dist: PyAutoGUI (==0.9.53)
Requires-Dist: pyparsing (==3.0.9)
Requires-Dist: python-dateutil (==2.8.2)
Requires-Dist: pytz (==2022.1)
Requires-Dist: PyYAML (==6.0)
Requires-Dist: regex (==2022.4.24)
Requires-Dist: schemdraw (==0.14)
Requires-Dist: scikit-learn (==1.0.2)
Requires-Dist: scipy (==1.8.0)
Requires-Dist: seaborn (==0.11.2)
Requires-Dist: shap (==0.41.0)
Requires-Dist: six (==1.16.0)
Requires-Dist: slicer (==0.0.7)
Requires-Dist: statsmodels (==0.13.2)
Requires-Dist: streamlit (==1.11.0)
Requires-Dist: streamlit-aggrid (==0.2.3.post2)
Requires-Dist: tenacity (==8.0.1)
Requires-Dist: threadpoolctl (==3.1.0)
Requires-Dist: tqdm (==4.64.0)
Requires-Dist: varname (==0.10.0)
Requires-Dist: Werkzeug (==1.0.1)
Requires-Dist: xgboost (==1.5.2)
